{"type":"list_page","items":[{"user":{"username":"admin","password":"$2a$10$VAF.FNvz1JqhCAB5rCh9GOa965eYWH3fcgWIuQFAmsZnnVS/.ye1y","full_name":"Administrator","email":"admin@cronicle.com","active":1,"modified":1560215331,"created":1560215331,"salt":"salty","privileges":{"admin":1}},"action":"user_login","epoch":1560215523,"ip":"10.255.0.2","headers":{"host":"cron.devdatalab.pl.eso.org","x-real-ip":"10.255.0.2","x-forwarded-for":"10.255.0.2","x-forwarded-host":"cron.devdatalab.pl.eso.org","connection":"upgrade","content-length":"39","accept":"text/plain, */*; q=0.01","origin":"http://cron.devdatalab.pl.eso.org:81","x-requested-with":"XMLHttpRequest","user-agent":"Mozilla/5.0 (Macintosh; Intel Mac OS X 10_13_3) AppleWebKit/537.36 (KHTML, like Gecko) Chrome/74.0.3729.169 Safari/537.36","content-type":"text/plain","referer":"http://cron.devdatalab.pl.eso.org:81/","accept-encoding":"gzip, deflate","accept-language":"en-US,en;q=0.9,es;q=0.8,de;q=0.7","cookie":"_ga=GA1.2.1747390184.1513163865; __utma=150389026.1747390184.1513163865.1532026210.1545692691.8; __utmz=150389026.1545692691.8.2.utmcsr=search.eso.org|utmccn=(referral)|utmcmd=referral|utmcct=/search; mjx.latest=2.7.5"},"username":"admin"},{"hostname":"jupyterhub_admin","action":"server_master","epoch":1560215392}]}